qr_verbose/qr_verbose.py
qr_verbose-1.0.0.dist-info/licenses/LICENSE
qr_verbose-1.0.0.dist-info/METADATA
qr_verbose-1.0.0.dist-info/WHEEL
qr_verbose-1.0.0.dist-info/entry_points.txt
qr_verbose-1.0.0.dist-info/top_level.txt
qr_verbose-1.0.0.dist-info/RECORD
