Metadata-Version: 2.4
Name: qr-verbose
Version: 1.0.0
Summary: A QR code generator with detailed visualization
Author-email: Nikolay Malkovsky <malkovskynv@gmail.com>
License: MIT
Project-URL: Homepage, https://sourcecraft.dev/malkovskynv/qr-verbose
Classifier: Programming Language :: Python :: 3
Classifier: License :: OSI Approved :: MIT License
Classifier: Operating System :: OS Independent
Requires-Python: >=3.6
License-File: LICENSE
Requires-Dist: qrcode
Requires-Dist: numpy
Requires-Dist: pillow
Dynamic: license-file
